azureml/__init__.py
azureml/interpret/__init__.py
azureml/interpret/mimic_wrapper.py
azureml/interpret/_internal/__init__.py
azureml/interpret/_internal/constants.py
azureml/interpret/_internal/explanation_client.py
azureml/interpret/common/__init__.py
azureml/interpret/common/exceptions.py
azureml/interpret/common/explanation_utils.py
azureml/interpret/common/model_summary.py
azureml/interpret/common/_errors/__init__.py
azureml/interpret/common/_errors/error_definitions.py
azureml/interpret/common/_errors/error_strings.py
azureml/interpret/common/constants/__init__.py
azureml/interpret/common/storage_policy/__init__.py
azureml/interpret/common/storage_policy/_storage_policy.py
azureml/interpret/model/__init__.py
azureml/interpret/model/serialize.py
azureml/interpret/scoring/__init__.py
azureml/interpret/scoring/scoring_explainer/__init__.py
azureml/interpret/scoring/scoring_explainer/_scoring_explainer.py
azureml_interpret-1.60.0.dist-info/licenses/LICENSE.txt
azureml_interpret-1.60.0.dist-info/METADATA
azureml_interpret-1.60.0.dist-info/WHEEL
azureml_interpret-1.60.0.dist-info/top_level.txt
azureml_interpret-1.60.0.dist-info/RECORD
