Metadata-Version: 2.4
Name: azureml-interpret
Version: 1.60.0
Summary: Machine Learning interpret package is used to interpret ML models
Home-page: https://docs.microsoft.com/python/api/overview/azure/ml/?view=azure-ml-py
Author: Microsoft Corp
License: https://aka.ms/azureml-sdk-license
Classifier: Development Status :: 5 - Production/Stable
Classifier: Intended Audience :: Developers
Classifier: Intended Audience :: Science/Research
Classifier: License :: Other/Proprietary License
Classifier: Programming Language :: Python :: 3
Classifier: Programming Language :: Python :: 3.8
Classifier: Programming Language :: Python :: 3.9
Classifier: Programming Language :: Python :: 3.10
Classifier: Programming Language :: Python :: 3.11
Classifier: Topic :: Scientific/Engineering :: Artificial Intelligence
Classifier: Operating System :: Microsoft :: Windows
Classifier: Operating System :: MacOS
Classifier: Operating System :: POSIX :: Linux
Requires-Python: >=3.8,<4.0
License-File: LICENSE.txt
Requires-Dist: interpret-community==0.31.*
Requires-Dist: numba<=0.56.4; python_version < "3.11"
Requires-Dist: numba<=0.58.1; python_version >= "3.11"
Requires-Dist: numpy<=1.21.6; python_version < "3.8"
Requires-Dist: numpy<=1.23.5; python_version >= "3.8"
Requires-Dist: azureml-core~=1.60.0
Provides-Extra: sample
Requires-Dist: interpret-community[sample]; extra == "sample"
Provides-Extra: deep
Requires-Dist: interpret-community[deep]; extra == "deep"
Provides-Extra: mimic
Requires-Dist: interpret-community[mimic]; extra == "mimic"
Dynamic: author
Dynamic: classifier
Dynamic: description
Dynamic: description-content-type
Dynamic: home-page
Dynamic: license
Dynamic: license-file
Dynamic: provides-extra
Dynamic: requires-dist
Dynamic: requires-python
Dynamic: summary
